{"cameraMode":{"drawMode":0,"name":"Shaded","section":"Shading Mode"},"sceneLighting":false,"audioPlay":false,"sceneViewState":{"m_AlwaysRefresh":false,"showFog":true,"showSkybox":false,"showFlares":true,"showImageEffects":true,"showParticleSystems":true,"showVisualEffectGraphs":true,"m_FxEnabled":true},"in2DMode":false,"pivot":{"x":-16.8389892578125,"y":0.8865013122558594,"z":-0.6703927516937256},"rotation":{"x":-0.1338375061750412,"y":0.8276646137237549,"z":-0.22266824543476106,"w":-0.49747633934020998},"size":1.8214609622955323,"orthographic":false}